kvgdb/__init__.py
kvgdb/exceptions.py
kvgdb/utils.py
kvgdb-0.1.1.dist-info/licenses/LICENSE
kvgdb-0.1.1.dist-info/METADATA
kvgdb-0.1.1.dist-info/WHEEL
kvgdb-0.1.1.dist-info/top_level.txt
kvgdb-0.1.1.dist-info/RECORD
